Metadata-Version: 2.1
Name: csvcubed-pydantic
Version: 1.9.0
Summary: Data validation and settings management using python 3.6 type hinting
Home-page: https://github.com/samuelcolvin/pydantic
Author: Samuel Colvin
Author-email: s@muelcolvin.com
License: MIT
Platform: UNKNOWN
Classifier: Development Status :: 5 - Production/Stable
Classifier: Programming Language :: Python
Classifier: Programming Language :: Python :: 3
Classifier: Programming Language :: Python :: 3 :: Only
Classifier: Programming Language :: Python :: 3.6
Classifier: Programming Language :: Python :: 3.7
Classifier: Programming Language :: Python :: 3.8
Classifier: Programming Language :: Python :: 3.9
Classifier: Programming Language :: Python :: 3.10
Classifier: Intended Audience :: Developers
Classifier: Intended Audience :: Information Technology
Classifier: Intended Audience :: System Administrators
Classifier: License :: OSI Approved :: MIT License
Classifier: Operating System :: Unix
Classifier: Operating System :: POSIX :: Linux
Classifier: Environment :: Console
Classifier: Environment :: MacOS X
Classifier: Framework :: Hypothesis
Classifier: Topic :: Software Development :: Libraries :: Python Modules
Classifier: Topic :: Internet
Requires-Python: >=3.6.1
License-File: LICENSE
Requires-Dist: typing-extensions (>=3.7.4.3)
Requires-Dist: dataclasses (>=0.6) ; python_version < "3.7"
Provides-Extra: dotenv
Requires-Dist: python-dotenv (>=0.10.4) ; extra == 'dotenv'
Provides-Extra: email
Requires-Dist: email-validator (>=1.0.3) ; extra == 'email'
